kbase_workspace_client/__init__.py
kbase_workspace_client/contigset_to_fasta.py
kbase_workspace_client/exceptions.py
kbase_workspace_client/main.py
kbase_workspace_client-0.2.1.dist-info/LICENSE.md
kbase_workspace_client-0.2.1.dist-info/WHEEL
kbase_workspace_client-0.2.1.dist-info/METADATA
kbase_workspace_client-0.2.1.dist-info/RECORD
